socketman/__init__.py
socketman/auto_socket.py
socketman/common.py
socketman/objsocket.py
socketman/serialization.py
socketman/socket.py
socketman/version.py
socketman/manager/__init__.py
socketman/manager/__main__.py
socketman/manager/_var.py
socketman/manager/client.py
socketman/manager/common.py
socketman/manager/cowork.py
socketman/manager/old_cowork.py
socketman/manager/server.py
socketman/manager/trashed/__init__.py
socketman/manager/trashed/__main__.py
socketman/manager/trashed/_var.py
socketman/manager/trashed/client.py
socketman/manager/trashed/cowork.py
socketman/manager/trashed/server.py
socketman/manager/trashed/server2.py
socketman-0.4.0.dist-info/LICENSE
socketman-0.4.0.dist-info/METADATA
socketman-0.4.0.dist-info/WHEEL
socketman-0.4.0.dist-info/top_level.txt
socketman-0.4.0.dist-info/RECORD
