Metadata-Version: 2.1
Name: socketman
Version: 0.4.0
Summary: Send arbitrary Python objects via websockets
Home-page: https://github.com/zlolss/SocketMan.py.git
Author: zlols
Author-email: zlols@foxmail.com
Classifier: Programming Language :: Python :: 3 :: Only
Classifier: License :: OSI Approved :: MIT License
Requires-Python: >=3.6
License-File: LICENSE
Requires-Dist: websockets
